FIFO_memory.sv
module fifo_memory # (parameter DEPTH=8, DATA_WIDTH=8, PTR_WIDTH=3) (wclk, rclk, wrst_n, rrst_n, w_en, r_en, b_wptr, b_rptr, full, empty, data_in, data_out);
  
  input wclk, rclk, wrst_n, rrst_n, w_en, r_en;
  input [PTR_WIDTH:0]b_wptr, b_rptr;
  input full, empty;
  input [DATA_WIDTH-1:0] data_in;
  output logic [DATA_WIDTH-1:0] data_out;
  
  reg  [DATA_WIDTH-1:0] fifo[0:DEPTH-1];
  
  always@(posedge wclk)
    begin
      if(w_en & !full)
        begin
          fifo[b_wptr[PTR_WIDTH-1:0]] <= data_in;
        end
    end
  
  assign data_out = fifo[b_rptr[PTR_WIDTH-1:0]];
endmodule

rptr_handler.sv
module rptr_handler(rclk, r_en, rrst_n, g_wptr_sync, b_rptr, g_rptr, empty);
  parameter PTR_WIDTH = 3; //fifo depth = 8 combinations (log2 8 : 3 bits)
  input rclk, r_en, rrst_n;
  input [PTR_WIDTH:0] g_wptr_sync;
  output reg [PTR_WIDTH:0] b_rptr, g_rptr;
  output reg empty;
  
  reg [PTR_WIDTH:0] b_rptr_next;
  reg [PTR_WIDTH:0] g_rptr_next;
  wire rempty;
  
  assign b_rptr_next = b_rptr + (r_en & !empty);//if condition true: updated the b_rptr by 1
  assign g_rptr_next = b_rptr_next>>1 ^ b_rptr_next;//bin to gray conversion
  //Empty Detect
  assign rempty = (g_wptr_sync == g_rptr_next);
  
  always@(posedge rclk or negedge rrst_n)
    begin
      if(!rrst_n)
        begin
          b_rptr <= 0;
          g_rptr <= 0;
        end
      else
        begin 
          b_rptr <= b_rptr_next;
          g_rptr <= g_rptr_next;
        end
    end
  
  always@(posedge rclk or negedge rrst_n)
    begin
      if(!rrst_n)
        empty <= 1;
      else
        empty <= rempty;
    end
endmodule

wptr_handler.sv
module wptr_handler(wclk, wrst_n, w_en, g_rptr_sync, b_wptr, g_wptr, full);
  parameter PTR_WIDTH = 3;
  input wclk, wrst_n, w_en;
  input [PTR_WIDTH:0] g_rptr_sync;
  output reg [PTR_WIDTH:0] b_wptr, g_wptr;
  output reg full;

  reg [PTR_WIDTH:0] b_wptr_next;
  reg [PTR_WIDTH:0] g_wptr_next;
  reg wrap_around;
  wire wfull;

  assign b_wptr_next = b_wptr + (w_en & !full); //if condition true = b_wptr will be increment by one
  assign g_wptr_next = b_wptr_next>>1 ^ b_wptr_next;

  //Full Detect
  assign wfull = g_wptr_next == {~g_rptr_sync[PTR_WIDTH:PTR_WIDTH-1], g_rptr_sync[PTR_WIDTH-2:0]};

  always@(posedge wclk or negedge wrst_n)
    if(!wrst_n)
      begin
        b_wptr <= 0;
        g_wptr <= 0;
      end
  else
    begin
      b_wptr <= b_wptr_next;
      g_wptr <= g_wptr_next;
    end

  always@(posedge wclk or negedge wrst_n)
    begin
      if(!wrst_n)
        full <= 0;
      else
        full <= wfull;
    end

endmodule

synchronizer.sv
module synchronizer (clk, rst_n, d_in, d_out);
  parameter WIDTH = 3;
  input clk, rst_n;
  input [WIDTH:0]d_in;
  output reg [WIDTH:0] d_out;
  
  reg [WIDTH:0] q1;
  
  always@(posedge clk or negedge rst_n)begin
  if(!rst_n)
    begin
      q1<=0;
      d_out<=0;
    end
  else 
    begin
      q1<=d_in;
      d_out<=q1;
    end
  end
endmodule

design.sv
`include "synchronizer.sv"
`include "wptr_handler.sv"
`include "rptr_handler.sv"
`include "FIFO_memory.sv"

module async_fifo # (parameter DATA_WIDTH = 8, DEPTH = 8)  (
  input wclk, rclk, 
  input wrst_n, rrst_n,
  input w_en, r_en,
  input [DATA_WIDTH-1:0] data_in,
  output reg [DATA_WIDTH-1:0] data_out,
  output reg full, empty
);

  parameter PTR_WIDTH = $clog2(DEPTH);

  reg [PTR_WIDTH:0] b_wptr, b_rptr;
  reg [PTR_WIDTH:0] g_wptr, g_rptr;
  reg [PTR_WIDTH:0] g_wptr_sync, g_rptr_sync;

  wire [PTR_WIDTH-1:0] waddr, raddr;

  synchronizer #(PTR_WIDTH) wptr_sync (wclk, wrst_n, g_rptr, g_rptr_sync); // read ptr -> write domain (for full)
  synchronizer #(PTR_WIDTH) rptr_sync (rclk, rrst_n, g_wptr, g_wptr_sync); // write ptr -> read domain (for empty)

  wptr_handler #(PTR_WIDTH) wptr_h (wclk, wrst_n, w_en, g_rptr_sync, b_wptr, g_wptr, full);
  rptr_handler #(PTR_WIDTH) rptr_h (rclk, r_en, rrst_n, g_wptr_sync, b_rptr, g_rptr, empty);

  fifo_memory fifo_mem(wclk, rclk, wrst_n, rrst_n, w_en, r_en, b_wptr, b_rptr, full, empty, data_in, data_out);
                                   
endmodule

testbench.sv
module asyc_fifo_tb;
  parameter DATA_WIDTH = 8;
  wire [DATA_WIDTH-1:0] data_out;
  wire full, empty;
  reg wclk, rclk;
  reg wrst_n, rrst_n;
  reg w_en, r_en;
  reg[DATA_WIDTH-1:0] data_in;
  
  reg [DATA_WIDTH-1:0] wdata_q[$], wdata;
  
  async_fifo dut(wclk, rclk, wrst_n, rrst_n, w_en, r_en, data_in, data_out, full, empty);
  
  always #10 wclk = ~wclk;
  always #35 rclk = ~rclk;
  
  initial begin
    wclk = 1'b0;
    wrst_n = 1'b0;
    w_en = 1'b0;
    data_in = 1'b0;

    repeat(10) @ (posedge wclk)
      wrst_n = 1'b1;//Holds reset for 10 write-clock edges, then deasserts reset (releases FIFO from reset).

    repeat(2) begin
      for(int i=0; i<30; i++) begin
        @(posedge wclk);          // no more "iff !full"
        #1;
        w_en = (i%2==0) ? 1'b1 : 1'b0;
        if (w_en && !full) begin              // <-- add !full check
          data_in = $random;
          wdata_q.push_back(data_in);
        end
      end
      #50;
      
      // after the main write loop, deliberately hammer w_en while full
      repeat(5) begin
        @(posedge wclk); #1;
        w_en = 1'b1;
        data_in = $random;
        if (!full) wdata_q.push_back(data_in);   // only counts if DUT actually accepts it
      end
    end
  end
  
  initial begin
    rclk = 1'b0;
    rrst_n = 1'b0;
    r_en = 1'b0;

    repeat(20) @ (posedge rclk)
      rrst_n = 1'b1;

    repeat(2) begin
      for(int i=0; i<30; i++) begin
        @(posedge rclk);           // no more "iff !empty"
        r_en = (i%2==0) ? 1'b1 : 1'b0;
        if (r_en && !empty) begin             // <-- add !empty check
          wdata = wdata_q.pop_front();
          if (data_out !== wdata)
            $error("Time = %0t Comparison Failed expected, w_data = %h, r_data = %h", $time, wdata, data_out);
          else
            $display("Time = %0t Comparison Passed, w_data = %h, r_data = %h", $time, wdata, data_out);
        end
      end
    #50;
  end
  $finish;
  end
  
  
  initial begin
    $dumpfile("dump.vcd");
    $dumpvars(0,asyc_fifo_tb);
  end
  
  
  //------Functional Coverage------

  covergroup fifo_cg @(posedge wclk);

    //Write enable
    w_en_cp : coverpoint w_en {
      bins disabled = {0};
      bins enabled  = {1};
    }

    //Read enable
    r_en_cp : coverpoint r_en {
      bins disabled = {0};
      bins enabled  = {1};
    }

    //FIFO full
    full_cp : coverpoint full {
      bins not_full = {0};
      bins full     = {1};
    }

    //FIFO empty
    empty_cp : coverpoint empty {
      bins not_empty = {0};
      bins empty     = {1};
    }

    //Cross coverage of control combinations
    write_full : cross w_en, full;
    read_empty : cross r_en, empty;

  endgroup

  fifo_cg cov = new();
  
  //------Coverage result------
  final begin

    $display("\n-----------------------------------------");
    $display("       FUNCTIONAL COVERAGE REPORT");
    $display("-----------------------------------------");
    $display("           Coverage = %0.2f%%", cov.get_coverage());
    $display("write_full = %0.2f", cov.write_full.get_coverage());
    $display("read_empty = %0.2f", cov.read_empty.get_coverage());
    $display("-----------------------------------------\n");

  end
  
endmodule

dump.vcd
$date
	Mon Aug 10 22:40:51 2026
$end

$version
	Synopsys VCS version X-2025.06-SP1_Full64
$end

$timescale
	1ns
$end

$comment Csum: 1 629fc040d742e1cf $end


$scope module asyc_fifo_tb $end
$var wire 8 ! data_out [7:0] $end
$var wire 1 " full $end
$var wire 1 # empty $end
$var reg 1 $ wclk $end
$var reg 1 % rclk $end
$var reg 1 & wrst_n $end
$var reg 1 ' rrst_n $end
$var reg 1 ( w_en $end
$var reg 1 ) r_en $end
$var reg 8 * data_in [7:0] $end
$var reg 8 + wdata [7:0] $end

$scope begin unnamed$$_vcs_5 $end
$upscope $end


$scope begin unnamed$$_vcs_0 $end
$upscope $end


$scope begin unnamed$$_vcs_1 $end
$upscope $end


$scope begin unnamed$$_vcs_2 $end
$upscope $end


$scope begin unnamed$$_vcs_3 $end

$scope begin unnamed$$_0 $end
$upscope $end

$upscope $end


$scope begin unnamed$$_vcs_4 $end

$scope begin unnamed$$_1 $end
$upscope $end

$upscope $end


$scope begin unnamed$$_vcs_6 $end
$upscope $end


$scope module dut $end
$var wire 1 $ wclk $end
$var wire 1 % rclk $end
$var wire 1 & wrst_n $end
$var wire 1 ' rrst_n $end
$var wire 1 ( w_en $end
$var wire 1 ) r_en $end
$var wire 8 * data_in [7:0] $end
$var reg 8 , data_out [7:0] $end
$var reg 1 - full $end
$var reg 1 . empty $end
$var reg 4 / b_wptr [3:0] $end
$var reg 4 0 b_rptr [3:0] $end
$var reg 4 1 g_wptr [3:0] $end
$var reg 4 2 g_rptr [3:0] $end
$var reg 4 3 g_wptr_sync [3:0] $end
$var reg 4 4 g_rptr_sync [3:0] $end
$var wire 3 5 waddr [2:0] $end
$var wire 3 6 raddr [2:0] $end

$scope module wptr_sync $end
$var wire 1 $ clk $end
$var wire 1 & rst_n $end
$var wire 4 2 d_in [3:0] $end
$var reg 4 4 d_out [3:0] $end
$var reg 4 7 q1 [3:0] $end
$upscope $end


$scope module rptr_sync $end
$var wire 1 % clk $end
$var wire 1 ' rst_n $end
$var wire 4 1 d_in [3:0] $end
$var reg 4 3 d_out [3:0] $end
$var reg 4 8 q1 [3:0] $end
$upscope $end


$scope module wptr_h $end
$var wire 1 $ wclk $end
$var wire 1 & wrst_n $end
$var wire 1 ( w_en $end
$var wire 4 4 g_rptr_sync [3:0] $end
$var reg 4 / b_wptr [3:0] $end
$var reg 4 1 g_wptr [3:0] $end
$var reg 1 - full $end
$var reg 4 9 b_wptr_next [3:0] $end
$var reg 4 : g_wptr_next [3:0] $end
$var reg 1 ; wrap_around $end
$var wire 1 < wfull $end
$upscope $end


$scope module rptr_h $end
$var wire 1 % rclk $end
$var wire 1 ) r_en $end
$var wire 1 ' rrst_n $end
$var wire 4 3 g_wptr_sync [3:0] $end
$var reg 4 0 b_rptr [3:0] $end
$var reg 4 2 g_rptr [3:0] $end
$var reg 1 . empty $end
$var reg 4 = b_rptr_next [3:0] $end
$var reg 4 > g_rptr_next [3:0] $end
$var wire 1 ? rempty $end
$upscope $end


$scope module fifo_mem $end
$var wire 1 $ wclk $end
$var wire 1 % rclk $end
$var wire 1 & wrst_n $end
$var wire 1 ' rrst_n $end
$var wire 1 ( w_en $end
$var wire 1 ) r_en $end
$var wire 4 / b_wptr [3:0] $end
$var wire 4 0 b_rptr [3:0] $end
$var wire 1 - full $end
$var wire 1 . empty $end
$var wire 8 * data_in [7:0] $end
$var reg 8 , data_out [7:0] $end
$upscope $end

$upscope $end

$upscope $end

$enddefinitions $end

#0
$dumpvars
1.
0-
1#
0"
0)
0%
1?
0'
0(
0$
0<
0&
b0000 0
b0000 =
b0000 /
b0000 9
b00000000 *
bxxxxxxxx !
bxxxxxxxx ,
b0000 2
b0000 >
b0000 4
b0000 1
b0000 :
b0000 3
b0000 7
b0000 8
bxxxxxxxx +
x;
bzzz 6
bzzz 5
$end
#10
1$
1&
#20
0$
#30
1$
#35
1%
1'
#40
0$
#50
1$
#60
0$
#70
0%
1$
#80
0$
#90
1$
#100
0$
#105
1%
#110
1$
#120
0$
#130
1$
#140
0%
0$
#150
1$
#160
0$
#170
1$
#175
1%
#180
0$
#190
1$
#200
0$
#210
0%
1$
#211
1(
b00100100 *
b0001 9
b0001 :
#220
0$
#230
1$
b0001 /
b0001 1
b00100100 ,
b00100100 !
b0010 9
b0011 :
#231
0(
b0001 9
b0001 :
#240
0$
#245
1%
b0001 8
#250
1$
#251
1(
b10000001 *
b0010 9
b0011 :
#260
0$
#270
1$
b0010 /
b0011 1
b0011 9
b0010 :
#271
0(
b0010 9
b0011 :
#280
0%
0$
#290
1$
#291
1(
b00001001 *
b0011 9
b0010 :
#300
0$
#310
1$
b0011 /
b0010 1
b0100 9
b0110 :
#311
0(
b0011 9
b0010 :
#315
1%
b0010 8
b0001 3
0?
#320
0$
#330
1$
#331
1(
b01100011 *
b0100 9
b0110 :
#340
0$
#350
0%
1$
b0100 /
b0110 1
b0101 9
b0111 :
#351
0(
b0100 9
b0110 :
#360
0$
#370
1$
#371
1(
b00001101 *
b0101 9
b0111 :
#380
0$
#385
1%
b0110 8
b0010 3
0.
0#
#390
1$
b0101 /
b0111 1
b0110 9
b0101 :
#391
0(
b0101 9
b0111 :
#400
0$
#410
1$
#411
1(
b10001101 *
b0110 9
b0101 :
#420
0%
0$
#430
1$
b0110 /
b0101 1
b0111 9
b0100 :
#431
0(
b0110 9
b0101 :
#440
0$
#450
1$
#451
1(
b01100101 *
b0111 9
b0100 :
#455
1%
b0101 8
b0110 3
#460
0$
#470
1$
b0111 /
b0100 1
b1000 9
b1100 :
1<
#471
0(
b0111 9
b0100 :
0<
#480
0$
#490
0%
1$
#491
1(
b00010010 *
b1000 9
b1100 :
1<
#500
0$
#510
1$
b1000 /
b1100 1
1-
1"
b1000 9
#511
0(
#520
0$
#525
1%
b1100 8
b0101 3
#530
1$
#531
1(
#540
0$
#550
1$
#551
0(
#560
0%
0$
#570
1$
#571
1(
#580
0$
#590
1$
#591
0(
#595
1%
b1100 3
#600
0$
#610
1$
#611
1(
#620
0$
#630
0%
1$
#631
0(
#640
0$
#650
1$
#651
1(
#660
0$
#665
1%
#670
1$
#671
0(
#680
0$
#690
1$
#691
1(
#700
0%
0$
#710
1$
#711
0(
#720
0$
#730
1$
#731
1(
#735
1%
#740
0$
#750
1$
#751
0(
#760
0$
#770
0%
1$
#771
1(
#780
0$
#790
1$
#791
0(
#800
0$
#805
1%
#810
1$
#820
0$
#830
1$
#840
0%
0$
#850
1$
#851
1(
b00000001 *
#860
0$
#870
1$
#871
b00001101 *
#875
1%
#880
0$
#890
1$
#891
b01110110 *
#900
0$
#910
0%
1$
#911
b00111101 *
#920
0$
#930
1$
#931
b11101101 *
#940
0$
#945
1%
#950
1$
#960
0$
#970
1$
#971
0(
#980
0%
0$
#990
1$
#991
1(
#1000
0$
#1010
1$
#1011
0(
#1015
1%
#1020
0$
#1030
1$
#1031
1(
#1040
0$
#1050
0%
1$
#1051
0(
#1060
0$
#1070
1$
#1071
1(
#1080
0$
#1085
1%
#1090
1$
#1091
0(
#1100
0$
#1110
1$
#1111
1(
#1120
0%
0$
#1130
1$
#1131
0(
#1140
0$
#1150
1$
#1151
1(
#1155
1%
#1160
0$
#1170
1$
#1171
0(
#1180
0$
#1190
0%
1$
#1191
1(
#1200
0$
#1210
1$
#1211
0(
#1220
0$
#1225
1%
#1230
1$
#1231
1(
#1240
0$
#1250
1$
#1251
0(
#1260
0%
0$
#1270
1$
#1271
1(
#1280
0$
#1290
1$
#1291
0(
#1295
1%
#1300
0$
#1310
1$
#1311
1(
#1320
0$
#1330
0%
1$
#1331
0(
#1340
0$
#1350
1$
#1351
1(
#1360
0$
#1365
1%
#1370
1$
#1371
0(
#1380
0$
#1390
1$
#1391
1(
#1400
0%
0$
#1410
1$
#1411
0(
#1420
0$
#1430
1$
#1431
1(
#1435
1%
1)
b00100100 +
b0001 =
b0001 >
#1440
0$
#1450
1$
#1451
0(
#1460
0$
#1470
0%
1$
#1471
1(
#1480
0$
#1490
1$
#1491
0(
#1500
0$
#1505
1%
0)
b0000 =
b0000 >
b0001 0
b10000001 ,
b10000001 !
b0001 2
b0001 =
b0001 >
#1510
1$
b0001 7
#1511
1(
#1520
0$
#1530
1$
b0001 4
0<
#1531
0(
#1540
0%
0$
#1550
1$
0-
0"
#1560
0$
#1570
1$
#1575
1%
1)
b10000001 +
b0010 =
b0010 >
b0011 >
#1580
0$
#1590
1$
#1591
1(
b10001100 *
b1001 9
b1101 :
1<
#1600
0$
#1610
0%
1$
b1001 /
b1101 1
1-
1"
b1001 9
#1611
b11111001 *
#1620
0$
#1630
1$
#1631
b11000110 *
#1640
0$
#1645
1%
0)
b0001 =
b0000 >
b0001 >
b1101 8
b0010 0
b00001001 ,
b00001001 !
b0011 2
b0010 =
b0010 >
b0011 >
#1650
1$
b0011 7
#1651
b11000101 *
#1660
0$
#1670
1$
b0011 4
0<
#1671
b10101010 *
#1680
0%
0$
#1690
1$
0-
0"
b1010 9
b1111 :
1<
#1700
0$
#1710
1$
b1010 /
b1111 1
1-
1"
b1010 9
#1715
1%
1)
b00001001 +
b0011 =
b0010 >
b1111 8
b1101 3
#1720
0$
#1730
1$
#1740
0$
#1750
0%
1$
#1760
0$
#1770
1$
#1780
0$
#1785
1%
0)
b0010 =
b0011 >
b1111 3
b0011 0
b01100011 ,
b01100011 !
b0010 2
b0011 =
b0010 >
#1790
1$
b0010 7
#1800
0$
#1810
1$
b0010 4
0<
#1820
0%
0$
#1830
1$
0-
0"
b1011 9
b1110 :
1<
#1840
0$
#1850
1$
b1011 /
b1110 1
1-
1"
b1011 9
#1855
1%
1)
b01100011 +
b0100 =
b0101 >
b0110 >
b1110 8
#1860
0$
#1870
1$
#1880
0$
#1890
0%
1$
#1900
0$
#1910
1$
#1920
0$
#1925
1%
0)
b0011 =
b0001 >
b0010 >
b1110 3
b0100 0
b00001101 ,
b00001101 !
b0110 2
b0100 =
b0101 >
b0110 >
#1930
1$
b0110 7
#1940
0$
#1950
1$
b0110 4
0<
#1960
0%
0$
#1970
1$
0-
0"
b1100 9
b1010 :
1<
#1980
0$
#1990
1$
b1100 /
b1010 1
1-
1"
b1100 9
#1995
1%
1)
b00001101 +
b0101 =
b0111 >
b1010 8
#2000
0$
#2010
1$
#2020
0$
#2030
0%
1$
#2040
0$
#2050
1$
#2060
0$
#2065
1%
0)
b0100 =
b0110 >
b1010 3
b0101 0
b10001101 ,
b10001101 !
b0111 2
b0101 =
b0111 >
#2070
1$
b0111 7
#2080
0$
#2090
1$
b0111 4
0<
#2100
0%
0$
#2110
1$
0-
0"
b1101 9
b1011 :
1<
#2120
0$
#2130
1$
b1101 /
b1011 1
1-
1"
b1101 9
#2135
1%
1)
b10001101 +
b0110 =
b0100 >
b0101 >
b1011 8
#2140
0$
#2150
1$
#2160
0$
#2170
0%
1$
#2180
0$
#2190
1$
#2200
0$
#2205
1%
0)
b0101 =
b0110 >
b0111 >
b1011 3
b0110 0
b01100101 ,
b01100101 !
b0101 2
b0110 =
b0100 >
b0101 >
#2210
1$
b0101 7
#2220
0$
#2230
1$
b0101 4
0<
#2240
0%
0$
#2250
1$
0-
0"
b1110 9
b1001 :
1<
#2260
0$
#2270
1$
b1110 /
b1001 1
1-
1"
b1110 9
#2275
1%
1)
b01100101 +
b0111 =
b0100 >
b1001 8
#2280
0$
#2290
1$
#2300
0$
#2310
0%
1$
#2320
0$
#2330
1$
#2340
0$
#2345
1%
0)
b0110 =
b0101 >
b1001 3
b0111 0
b00010010 ,
b00010010 !
b0100 2
b0111 =
b0100 >
#2350
1$
b0100 7
#2360
0$
#2370
1$
b0100 4
0<
#2380
0%
0$
#2390
1$
0-
0"
b1111 9
b1000 :
1<
#2400
0$
#2410
1$
b1111 /
b1000 1
1-
1"
b1111 9
#2415
1%
1)
b00010010 +
b1000 =
b1011 >
b1100 >
b1000 8
#2420
0$
#2430
1$
#2440
0$
#2450
0%
1$
#2460
0$
#2470
1$
#2480
0$
#2485
1%
0)
b0111 =
b0011 >
b0100 >
b1000 3
b1000 0
b10001100 ,
b10001100 !
b1100 2
b1000 =
b1011 >
b1100 >
#2490
1$
b1100 7
#2500
0$
#2510
1$
b1100 4
0<
#2520
0%
0$
#2530
1$
0-
0"
b0000 9
b0000 :
1<
#2540
0$
#2550
1$
b0000 /
b0000 1
1-
1"
b0000 9
#2555
1%
1)
b10001100 +
b1001 =
b1101 >
b0000 8
#2560
0$
#2570
1$
#2580
0$
#2590
0%
1$
#2600
0$
#2610
1$
#2620
0$
#2625
1%
0)
b1000 =
b1100 >
b0000 3
b1001 0
b10101010 ,
b10101010 !
b1101 2
b1001 =
b1101 >
#2630
1$
b1101 7
#2640
0$
#2650
1$
b1101 4
0<
#2660
0%
0$
#2670
1$
0-
0"
b0001 9
b0001 :
1<
#2680
0$
#2690
1$
b0001 /
b0001 1
1-
1"
b0001 9
#2695
1%
1)
bxxxxxxxx +
b1010 =
b1110 >
b1111 >
b0001 8
#2700
0$
#2710
1$
#2720
0$
#2730
0%
1$
#2740
0$
#2750
1$
#2760
0$
#2765
1%
0)
b1001 =
b1100 >
b1101 >
b0001 3
b1010 0
b1111 2
b1010 =
b1110 >
b1111 >
#2770
1$
b1111 7
#2780
0$
#2790
1$
b1111 4
0<
#2800
0%
0$
#2810
1$
0-
0"
b0010 9
b0011 :
1<
#2820
0$
#2830
1$
b0010 /
b0011 1
1-
1"
b0010 9
#2835
1%
1)
b1011 =
b1110 >
b0011 8
#2840
0$
#2850
1$
#2860
0$
#2870
0%
1$
#2880
0$
#2890
1$
#2900
0$
#2905
1%
0)
b1010 =
b1111 >
b0011 3
b1011 0
b1110 2
b1011 =
b1110 >
#2910
1$
b1110 7
#2920
0$
#2930
1$
b1110 4
0<
#2940
0%
0$
#2950
1$
0-
0"
b0011 9
b0010 :
1<
#2960
0$
#2970
1$
b0011 /
b0010 1
1-
1"
b0011 9
#2975
1%
1)
b1100 =
b1001 >
b1010 >
b0010 8
#2980
0$
#2990
1$
#3000
0$
#3010
0%
1$
#3020
0$
#3030
1$
#3040
0$
#3045
1%
0)
b1011 =
b1101 >
b1110 >
b0010 3
b1100 0
b1010 2
b1100 =
b1001 >
b1010 >
#3050
1$
b1010 7
#3060
0$
#3070
1$
b1010 4
0<
#3080
0%
0$
#3090
1$
0-
0"
b0100 9
b0110 :
1<
#3100
0$
#3110
1$
b0100 /
b0110 1
1-
1"
b0100 9
#3115
1%
1)
b1101 =
b1011 >
b0110 8
#3120
0$
#3130
1$
#3140
0$
#3150
0%
1$
#3160
0$
#3170
1$
#3180
0$
#3185
1%
0)
b1100 =
b1010 >
b0110 3
b1101 0
b1011 2
b1101 =
b1011 >
#3190
1$
b1011 7
#3200
0$
#3210
1$
b1011 4
0<
#3220
0%
0$
#3230
1$
0-
0"
b0101 9
b0111 :
1<
#3240
0$
#3250
1$
b0101 /
b0111 1
1-
1"
b0101 9
#3255
1%
1)
b1110 =
b1000 >
b1001 >
b0111 8
#3260
0$
#3270
1$
#3280
0$
#3290
0%
1$
#3300
0$
#3310
1$
#3320
0$
#3325
1%
0)
b1101 =
b1010 >
b1011 >
b0111 3
b1110 0
b1001 2
b1110 =
b1000 >
b1001 >
#3330
1$
b1001 7
#3340
0$
#3350
1$
b1001 4
0<
#3360
0%
0$
#3370
1$
0-
0"
b0110 9
b0101 :
1<
#3380
0$
#3390
1$
b0110 /
b0101 1
1-
1"
b0110 9
#3395
1%
1)
b1111 =
b1000 >
b0101 8
#3400
0$
#3410
1$
#3420
0$
#3430
0%
1$
#3440
0$
#3450
1$
#3460
0$
#3465
1%
0)
b1110 =
b1001 >
b0101 3
b1111 0
b1000 2
b1111 =
b1000 >
#3470
1$
b1000 7
#3480
0$
#3490
1$
b1000 4
0<
#3500
0%
0$
#3510
1$
0-
0"
b0111 9
b0100 :
1<
#3520
0$
#3530
1$
b0111 /
b0100 1
1-
1"
b0111 9
#3535
1%
1)
b0000 =
b0111 >
b0000 >
b0100 8
#3540
0$
#3550
1$
#3560
0$
#3570
0%
1$
#3580
0$
#3590
1$
#3600
0$
#3605
1%
0)
b1111 =
b1111 >
b1000 >
b0100 3
b0000 0
b0000 2
b0000 =
b0111 >
b0000 >
#3610
1$
b0000 7
#3620
0$
#3630
1$
b0000 4
0<
#3640
0%
0$
#3650
1$
0-
0"
b1000 9
b1100 :
1<
#3660
0$
#3670
1$
b1000 /
b1100 1
1-
1"
b1000 9
#3675
1%
1)
b0001 =
b0001 >
b1100 8
#3680
0$
#3690
1$
#3700
0$
#3710
0%
1$
#3720
0$
#3730
1$
#3740
0$
#3745
1%
0)
b0000 =
b0000 >
b1100 3
b0001 0
b0001 2
b0001 =
b0001 >
#3750
1$
b0001 7
#3760
0$
#3770
1$
b0001 4
0<
#3780
0%
0$
#3790
1$
0-
0"
b1001 9
b1101 :
1<
#3800
0$
#3810
1$
b1001 /
b1101 1
1-
1"
b1001 9
#3815
1%
1)
b0010 =
b0010 >
b0011 >
b1101 8
#3820
0$
#3830
1$
#3840
0$
#3850
0%
1$
#3860
0$
#3870
1$
#3880
0$
#3885
1%
0)
b0001 =
b0000 >
b0001 >
b1101 3
b0010 0
b0011 2
b0010 =
b0010 >
b0011 >
#3890
1$
b0011 7
#3900
0$
#3910
1$
b0011 4
0<
#3920
0%
0$
#3930
1$
0-
0"
b1010 9
b1111 :
1<
#3940
0$
#3950
1$
b1010 /
b1111 1
1-
1"
b1010 9
#3955
1%
1)
b0011 =
b0010 >
b1111 8
#3960
0$
#3970
1$
#3980
0$
#3990
0%
1$
#4000
0$
#4010
1$
#4020
0$
#4025
1%
0)
b0010 =
b0011 >
b1111 3
b0011 0
b0010 2
b0011 =
b0010 >
#4030
1$
b0010 7
#4040
0$
#4050
1$
b0010 4
0<
#4060
0%
0$
#4070
1$
0-
0"
b1011 9
b1110 :
1<
#4080
0$
#4090
1$
b1011 /
b1110 1
1-
1"
b1011 9
#4095
1%
1)
b0100 =
b0101 >
b0110 >
b1110 8
#4100
0$
#4110
1$
#4120
0$
#4130
0%
1$
#4140
0$
#4150
1$
#4160
0$
#4165
1%
0)
b0011 =
b0001 >
b0010 >
b1110 3
b0100 0
b0110 2
b0100 =
b0101 >
b0110 >
#4170
1$
b0110 7
#4180
0$
#4190
1$
b0110 4
0<
#4200
0%
0$
#4210
1$
0-
0"
b1100 9
b1010 :
1<
#4220
0$
#4230
1$
b1100 /
b1010 1
1-
1"
b1100 9
#4235
1%
1)
b0101 =
b0111 >
b1010 8
#4240
0$
#4250
1$
#4260
0$
#4270
0%
1$
#4280
0$
#4290
1$
#4300
0$
#4305
1%
0)
b0100 =
b0110 >
b1010 3
b0101 0
b0111 2
b0101 =
b0111 >
#4310
1$
b0111 7
#4320
0$
#4330
1$
b0111 4
0<
#4340
0%
0$
#4350
1$
0-
0"
b1101 9
b1011 :
1<
#4360
0$
#4370
1$
b1101 /
b1011 1
1-
1"
b1101 9
#4375
1%
1)
b0110 =
b0100 >
b0101 >
b1011 8
#4380
0$
#4390
1$
#4400
0$
#4410
0%
1$
#4420
0$
#4430
1$
#4440
0$
#4445
1%
0)
b0101 =
b0110 >
b0111 >
b1011 3
b0110 0
b0101 2
b0110 =
b0100 >
b0101 >
#4450
1$
b0101 7
#4460
0$
#4470
1$
b0101 4
0<
#4480
0%
0$
#4490
1$
0-
0"
b1110 9
b1001 :
1<
#4500
0$
#4510
1$
b1110 /
b1001 1
1-
1"
b1110 9
#4515
1%
1)
b0111 =
b0100 >
b1001 8
#4520
0$
#4530
1$
#4540
0$
#4550
0%
1$
#4560
0$
#4570
1$
#4580
0$
#4585
1%
0)
b0110 =
b0101 >
b1001 3
b0111 0
b0100 2
b0111 =
b0100 >
#4590
1$
b0100 7
#4600
0$
#4610
1$
b0100 4
0<
#4620
0%
0$
#4630
1$
0-
0"
b1111 9
b1000 :
1<
#4640
0$
#4650
1$
b1111 /
b1000 1
1-
1"
b1111 9
#4655
1%
1)
b1000 =
b1011 >
b1100 >
b1000 8
#4660
0$
#4670
1$
#4680
0$
#4690
0%
1$
#4700
0$
#4710
1$
#4720
0$
#4725
1%
0)
b0111 =
b0011 >
b0100 >
b1000 3
b1000 0
b1100 2
b1000 =
b1011 >
b1100 >
#4730
1$
b1100 7
#4740
0$
#4750
1$
b1100 4
0<
#4760
0%
0$
#4770
1$
0-
0"
b0000 9
b0000 :
1<
#4780
0$
#4790
1$
b0000 /
b0000 1
1-
1"
b0000 9
#4795
1%
1)
b1001 =
b1101 >
b0000 8
#4800
0$
#4810
1$
#4820
0$
#4830
0%
1$
#4840
0$
#4850
1$
#4860
0$
#4865
1%
0)
b1000 =
b1100 >
b0000 3
b1001 0
b1101 2
b1001 =
b1101 >
#4870
1$
b1101 7
#4880
0$
#4890
1$
b1101 4
0<
#4900
0%
0$
#4910
1$
0-
0"
b0001 9
b0001 :
1<
#4920
0$
#4930
1$
b0001 /
b0001 1
1-
1"
b0001 9
#4935
1%
1)
b1010 =
b1110 >
b1111 >
b0001 8
#4940
0$
#4950
1$
#4960
0$
#4970
0%
1$
#4980
0$
#4990
1$
#5000
0$
#5005
1%
0)
b1001 =
b1100 >
b1101 >
b0001 3
b1010 0
b1111 2
b1010 =
b1110 >
b1111 >
#5010
1$
b1111 7
#5020
0$
#5030
1$
b1111 4
0<
#5040
0%
0$
#5050
1$
0-
0"
b0010 9
b0011 :
1<
#5060
0$
#5070
1$
b0010 /
b0011 1
1-
1"
b0010 9
#5075
1%
1)
b1011 =
b1110 >
b0011 8
#5080
0$
#5090
1$
#5100
0$
#5110
0%
1$
#5120
0$
#5130
1$
#5140
0$
#5145
1%
0)
b1010 =
b1111 >
b0011 3
b1011 0
b1110 2
b1011 =
b1110 >
#5150
1$
b1110 7
#5160
0$
#5170
1$
b1110 4
0<
#5180
0%
0$
#5190
1$
0-
0"
b0011 9
b0010 :
1<
#5200
0$
#5210
1$
b0011 /
b0010 1
1-
1"
b0011 9
#5215
1%
1)
b1100 =
b1001 >
b1010 >
b0010 8
#5220
0$
#5230
1$
#5240
0$
#5250
0%
1$
#5260
0$
#5270
1$
